python_base_toolkit/__init__.py
python_base_toolkit/base_structures/__init__.py
python_base_toolkit/base_structures/base_enum.py
python_base_toolkit/ci/task_files/default.yml
python_base_toolkit/ci/task_files/dependencies.yml
python_base_toolkit/ci/task_files/deploy.yml
python_base_toolkit/ci/task_files/docker.yml
python_base_toolkit/ci/task_files/includes.yml
python_base_toolkit/ci/task_files/install.yml
python_base_toolkit/ci/task_files/lint.yml
python_base_toolkit/ci/task_files/vars.yml
python_base_toolkit/consts/__init__.py
python_base_toolkit/consts/operating_system.py
python_base_toolkit/consts/units/__init__.py
python_base_toolkit/consts/units/binary_units.py
python_base_toolkit/consts/units/time_units.py
python_base_toolkit/decorators/__init__.py
python_base_toolkit/decorators/telemetry.py
python_base_toolkit/decorators/timer.py
python_base_toolkit/instances/__init__.py
python_base_toolkit/instances/instance_manager.py
python_base_toolkit/scripts/__init__.py
python_base_toolkit/scripts/remove_build_files.py
python_base_toolkit/utils/__init__.py
python_base_toolkit/utils/data_serialization.py
python_base_toolkit/utils/date_time.py
python_base_toolkit/utils/execute.py
python_base_toolkit/utils/file_utils.py
python_base_toolkit/utils/generate_id.py
python_base_toolkit/utils/logo.py
python_base_toolkit/utils/network.py
python_base_toolkit/utils/path_utils.py
python_base_toolkit/utils/pretty_print.py
python_base_toolkit/utils/pycache.py
python_base_toolkit/utils/random_utils.py
python_base_toolkit/utils/shorten_url.py
python_base_toolkit/utils/venv_details.py
python_base_toolkit-0.0.17.dist-info/licenses/LICENSE
python_base_toolkit-0.0.17.dist-info/METADATA
python_base_toolkit-0.0.17.dist-info/WHEEL
python_base_toolkit-0.0.17.dist-info/top_level.txt
python_base_toolkit-0.0.17.dist-info/RECORD
