Metadata-Version: 2.4
Name: python-base-toolkit
Version: 0.0.17
Summary: A Python package for managing pytest plugins.
Author: Avi Zaguri
License: MIT
Project-URL: Homepage, https://github.com/aviz92/python-base-toolkit
Project-URL: Repository, https://github.com/aviz92/python-base-toolkit
Project-URL: Issues, https://github.com/aviz92/python-base-toolkit/issues
Keywords: development,python,toolkit,utilities
Classifier: Development Status :: 4 - Beta
Classifier: Intended Audience :: Developers
Classifier: Programming Language :: Python :: 3.11
Classifier: Operating System :: OS Independent
Classifier: Topic :: System :: Logging
Requires-Python: >=3.11
License-File: LICENSE
Requires-Dist: build>=1.3.0
Requires-Dist: colorlog>=6.10.1
Requires-Dist: custom-python-logger>=2.0.11
Requires-Dist: pandas>=2.3.3
Requires-Dist: pathlib>=1.0.1
Requires-Dist: pre-commit>=4.5.0
Requires-Dist: pyfiglet>=1.0.4
Requires-Dist: python-dotenv>=1.2.1
Requires-Dist: pyyaml>=6.0.3
Requires-Dist: requests>=2.32.5
Requires-Dist: setuptools>=80.9.0
Requires-Dist: tqdm>=4.67.1
Requires-Dist: twine>=6.2.0
Requires-Dist: wheel>=0.45.1
Dynamic: license-file
